mrt_downloader/__init__.py
mrt_downloader/cli.py
mrt_downloader/collector_index.py
mrt_downloader/collectors.py
mrt_downloader/download.py
mrt_downloader/files.py
mrt_downloader/http.py
mrt_downloader/models.py
mrt_downloader-0.0.6.dist-info/WHEEL
mrt_downloader-0.0.6.dist-info/entry_points.txt
mrt_downloader-0.0.6.dist-info/METADATA
mrt_downloader-0.0.6.dist-info/RECORD
