Metadata-Version: 2.3
Name: mrt-downloader
Version: 0.0.6
Summary: 
Author: Ties de Kock
Author-email: Ties de Kock <ties@tiesdekock.nl>
Requires-Dist: aiohttp>=3.13.1
Requires-Dist: click>=8.3
Requires-Dist: typing-extensions>=4.14.1
Requires-Python: >=3.11
